pyrga/RGA.py
pyrga/__init__.py
pyrga/gwsolver_2D_steady_state.py
pyrga/gwsolver_2D_transient.py
pyrga/hydraulic_tomography.py
pyrga/hydraulic_tomography_parallel.py
pyrga/utils.py
pyrga_ht-0.1.4.dist-info/licenses/LICENSE
pyrga_ht-0.1.4.dist-info/METADATA
pyrga_ht-0.1.4.dist-info/WHEEL
pyrga_ht-0.1.4.dist-info/top_level.txt
pyrga_ht-0.1.4.dist-info/RECORD
