Metadata-Version: 2.4
Name: pyrga-ht
Version: 0.1.4
Summary: A Python package for groundwater flow simulation and hydraulic tomography using the Reformulated Geostatistical Approach (RGA)
Home-page: https://github.com/QuanGuo/pyRGA
Author: Quan Guo
Author-email: qguo48@hotmail.com
Classifier: Development Status :: 3 - Alpha
Classifier: Intended Audience :: Science/Research
Classifier: License :: OSI Approved :: MIT License
Classifier: Operating System :: OS Independent
Classifier: Programming Language :: Python :: 3
Classifier: Programming Language :: Python :: 3.10
Classifier: Topic :: Scientific/Engineering :: Mathematics
Requires-Python: >=3.10
License-File: LICENSE
Requires-Dist: numpy>=1.21
Requires-Dist: scipy>=1.8
Requires-Dist: matplotlib>=3.5
Requires-Dist: pyamg>=4.2
Requires-Dist: mat73
Requires-Dist: joblib
Dynamic: author
Dynamic: author-email
Dynamic: classifier
Dynamic: description
Dynamic: description-content-type
Dynamic: home-page
Dynamic: license-file
Dynamic: requires-dist
Dynamic: requires-python
Dynamic: summary
